belvo/__init__.py
belvo/client.py
belvo/enums.py
belvo/exceptions.py
belvo/http.py
belvo/investments/__init__.py
belvo/investments/portfolios.py
belvo/resources/__init__.py
belvo/resources/accounts.py
belvo/resources/balances.py
belvo/resources/base.py
belvo/resources/employment_records.py
belvo/resources/incomes.py
belvo/resources/institutions.py
belvo/resources/invoices.py
belvo/resources/links.py
belvo/resources/owners.py
belvo/resources/recurring_expenses.py
belvo/resources/risk_insights.py
belvo/resources/statements.py
belvo/resources/tax_compliance_status.py
belvo/resources/tax_declarations.py
belvo/resources/tax_retentions.py
belvo/resources/tax_returns.py
belvo/resources/tax_status.py
belvo/resources/transactions.py
belvo/resources/widget_token.py
belvo_python-0.39.1.dist-info/LICENSE
belvo_python-0.39.1.dist-info/METADATA
belvo_python-0.39.1.dist-info/WHEEL
belvo_python-0.39.1.dist-info/top_level.txt
belvo_python-0.39.1.dist-info/RECORD
