Metadata-Version: 2.1
Name: belvo-python
Version: 0.39.1
Summary: Belvo Python SDK
Home-page: https://github.com/belvo-finance/belvo-python
Download-URL: https://github.com/belvo-finance/belvo-python/tarball/master
Author: Belvo Finance, S.L.
Author-email: hello@belvo.com
Keywords: api,belvo,sdk,finances,openbanking
Classifier: Development Status :: 3 - Alpha
Classifier: Environment :: Web Environment
Classifier: Intended Audience :: Developers
Classifier: License :: OSI Approved :: Apache Software License
Classifier: Operating System :: OS Independent
Classifier: Programming Language :: Python
Classifier: Programming Language :: Python :: 3
Classifier: Programming Language :: Python :: 3.6
Classifier: Programming Language :: Python :: 3.7
Classifier: Programming Language :: Python :: 3.8
Classifier: Topic :: Internet :: WWW/HTTP
Classifier: Topic :: Internet :: WWW/HTTP :: Dynamic Content
Requires-Python: >=3.6, <4
License-File: LICENSE
Requires-Dist: requests >=2.31.0
